concrete_mailer/__init__.py
concrete_mailer/client.py
concrete_mailer/preparers.py
concrete_mailer/utils.py
concrete_mailer-2.17.0.dist-info/LICENSE
concrete_mailer-2.17.0.dist-info/METADATA
concrete_mailer-2.17.0.dist-info/WHEEL
concrete_mailer-2.17.0.dist-info/top_level.txt
concrete_mailer-2.17.0.dist-info/RECORD
