Metadata-Version: 2.1
Name: concrete-mailer
Version: 2.17.0
Summary: Python package for sending rich e-mails.
Home-page: https://github.com/Netsach/concrete-mailer/
Author: Netsach
Author-email: contact@netsach.org
License: GNU GENERAL PUBLIC LICENSE Version 3
Project-URL: Bug Tracker, https://github.com/Netsach/concrete-mailer/issues
Project-URL: Documentation, https://github.com/Netsach/concrete-mailer/blob/master/README.md
Project-URL: Source Code, https://github.com/Netsach/concrete-mailer/
Platform: UNKNOWN
Classifier: Programming Language :: Python :: 2.7
Classifier: Programming Language :: Python :: 3.6
Classifier: Programming Language :: Python :: 3.7
Classifier: Programming Language :: Python :: 3.8
Requires-Dist: premailer (<4,>=3.6.1)
Requires-Dist: beautifulsoup4 (<5,>=4.8.0)
Requires-Dist: jinja2 (<3,>=2.10.1)
Provides-Extra: quality
Requires-Dist: pylint ; extra == 'quality'
Requires-Dist: black ; (python_version >= "3.6") and extra == 'quality'
Provides-Extra: security
Requires-Dist: bandit ; extra == 'security'
Provides-Extra: tests
Requires-Dist: mock ; extra == 'tests'
Requires-Dist: pytest-cov ; extra == 'tests'
Requires-Dist: pytest ; extra == 'tests'
Requires-Dist: codecov ; extra == 'tests'
